oui/__init__.py
oui/color_util.py
oui/util.py
oui/config_crud/config_files/some_json_config.json
oui/config_crud/config_files/dir/some_json_config.json
oui/config_crud/config_files/dir/json/some_json_config.json
oui/config_crud/config_files/json/some_json_config.json
oui/confusion_chords/__init__.py
oui/confusion_chords/chord_chart.js
oui/data/color_names_and_codes.json
oui/js/__init__.py
oui/js/index.js
oui/multi_time_vis/__init__.py
oui/multi_time_vis/audio.py
oui/multi_time_vis/base.py
oui/multi_time_vis/test/__init__.py
oui/multi_time_vis/test/audio_test.py
oui/nested-data-crud/public/manifest.json
oui/nested-data-crud/src/App.js
oui/nested-data-crud/src/App.test.js
oui/nested-data-crud/src/index.js
oui/nested-data-crud/src/serviceWorker.js
oui/nested-data-crud/src/setupTests.js
oui/nested-data-crud/src/nested-data-crud/index.js
oui/nested-data-crud/src/nested-data-crud/nested-data-crud.js
oui/sound_utils/fft-webworker.js
oui/splatter/__init__.py
oui/splatter/splatter_defaults.json
oui/splatter/umap.py
oui-0.3.3.dist-info/LICENSE
oui-0.3.3.dist-info/METADATA
oui-0.3.3.dist-info/WHEEL
oui-0.3.3.dist-info/top_level.txt
oui-0.3.3.dist-info/RECORD
