Metadata-Version: 2.1
Name: oui
Version: 0.3.3
Summary: There is a bit of an air of mystery around this project...
Home-page: https://github.com/otosense/oui
License: mit
Keywords: User Interface,UI,sound recognition
Platform: any
License-File: LICENSE
Requires-Dist: argh
